AUTHORS.rst
LICENSE
MANIFEST.in
README.rst
buildout.cfg
develop.cfg
pyproject.toml
requirements.txt
setup.py
version.txt
beat/__init__.py
beat.cmdline.egg-info/PKG-INFO
beat.cmdline.egg-info/SOURCES.txt
beat.cmdline.egg-info/dependency_links.txt
beat.cmdline.egg-info/entry_points.txt
beat.cmdline.egg-info/not-zip-safe
beat.cmdline.egg-info/requires.txt
beat.cmdline.egg-info/top_level.txt
beat/cmdline/__init__.py
beat/cmdline/algorithms.py
beat/cmdline/cache.py
beat/cmdline/click_helper.py
beat/cmdline/commands.py
beat/cmdline/common.py
beat/cmdline/config.py
beat/cmdline/databases.py
beat/cmdline/dataformats.py
beat/cmdline/decorators.py
beat/cmdline/environments.py
beat/cmdline/experiments.py
beat/cmdline/libraries.py
beat/cmdline/log.py
beat/cmdline/plotterparameters.py
beat/cmdline/plotters.py
beat/cmdline/protocoltemplates.py
beat/cmdline/status.py
beat/cmdline/toolchains.py
beat/cmdline/version.py
beat/cmdline/webapi.py
beat/cmdline/scripts/__init__.py
beat/cmdline/scripts/main_cli.py
beat/cmdline/test/__init__.py
beat/cmdline/test/core.py
beat/cmdline/test/test_algorithms.py
beat/cmdline/test/test_cache.py
beat/cmdline/test/test_config.py
beat/cmdline/test/test_databases.py
beat/cmdline/test/test_dataformats.py
beat/cmdline/test/test_docker.py
beat/cmdline/test/test_environments.py
beat/cmdline/test/test_experiments.py
beat/cmdline/test/test_libraries.py
beat/cmdline/test/test_plotterparameters.py
beat/cmdline/test/test_plotters.py
beat/cmdline/test/test_protocoltemplates.py
beat/cmdline/test/test_shortcuts.py
beat/cmdline/test/test_status.py
beat/cmdline/test/test_toolchains.py
beat/cmdline/test/utils.py
beat/cmdline/test/instructions/0123456789AAAAAAAAAAAAAAAAAAAAAAAAAAAAAAAAAAAAAAAAAAAAAAAA.0.9.data
beat/cmdline/test/instructions/0123456789AAAAAAAAAAAAAAAAAAAAAAAAAAAAAAAAAAAAAAAAAAAAAAAA.0.9.data.checksum
beat/cmdline/test/instructions/0123456789AAAAAAAAAAAAAAAAAAAAAAAAAAAAAAAAAAAAAAAAAAAAAAAA.0.9.index
beat/cmdline/test/instructions/0123456789AAAAAAAAAAAAAAAAAAAAAAAAAAAAAAAAAAAAAAAAAAAAAAAA.0.9.index.checksum
beat/cmdline/test/instructions/algo_using_cached_files.json
beat/cmdline/test/instructions/algo_using_database.json
beat/cmdline/test/instructions/algo_using_database_and_cached_files.json
