Metadata-Version: 2.1
Name: beat.cmdline
Version: 1.10.3
Summary: Command-line client for the BEAT platform
Home-page: https://gitlab.idiap.ch/beat/beat.cmdline
Author: Idiap Research Institute
Author-email: beat.support@idiap.ch
License: BSD
Classifier: Framework :: BEAT
Classifier: Development Status :: 5 - Production/Stable
Classifier: Intended Audience :: Developers
Classifier: License :: OSI Approved :: BSD License
Classifier: Natural Language :: English
Classifier: Programming Language :: Python
Classifier: Programming Language :: Python :: 3
Classifier: Topic :: Software Development :: Libraries :: Python Modules
License-File: LICENSE
License-File: AUTHORS.rst
